{
  "products": [
    { "id": 1, "price": "40000", "title": "Samsung" },
    { "id": 2, "price": "30000", "title": "Sony" },
    { "id": 3, "price": "24000", "title": "Apple" },
    { "id": 4, "price": "54000", "title": "MicroSoft" },
    { "id": 5, "price": "65000", "title": "Dell" },
    { "id": 6, "price": "23000", "title": "Lenovo" },
    { "id": 7, "price": "13000", "title": "HP" },
    { "id": 8, "price": "54000", "title": "Asus" },
    { "id": 9, "price": "23000", "title": "Idea" },
    { "id": 10, "price": "23400", "title": "NoIdea" },
    { "id": 11, "price": "61000", "title": "Vertue" }
  ],
  "courses": [
    {
      "id": 1,
      "title": "React",
      "price": "22000",
      "duration": "22 HRS",
      "selected": false
    },
    {
      "id": 2,
      "title": "Angular",
      "price": "15000",
      "duration": "14 HRS",
      "selected": false
    },
    {
      "id": 3,
      "title": "Ionic",
      "price": "15000",
      "duration": "15 HRS",
      "selected": false
    },
    {
      "id": 4,
      "title": "JavaScript",
      "price": "17000",
      "duration": "20 HRS",
      "selected": false
    },
    {
      "id": 5,
      "title": "TypeScript",
      "price": "10000",
      "duration": "7 HRS",
      "selected": false
    },
    {
      "id": 6,
      "title": "Hybernate",
      "price": "18000",
      "duration": "16 HRS",
      "selected": false
    },
    {
      "id": 7,
      "title": "Vue",
      "price": "24000",
      "duration": "10 HRS",
      "selected": false
    }
  ]
}
